sftpserver/__init__.py
sftpserver/stub_sftp.py
sftpserver-0.3.dist-info/DESCRIPTION.rst
sftpserver-0.3.dist-info/METADATA
sftpserver-0.3.dist-info/RECORD
sftpserver-0.3.dist-info/WHEEL
sftpserver-0.3.dist-info/entry_points.txt
sftpserver-0.3.dist-info/metadata.json
sftpserver-0.3.dist-info/top_level.txt
