Metadata-Version: 2.0
Name: sftpserver
Version: 0.3
Summary: sftpserver - a simple single-threaded sftp server
Home-page: http://github.com/rspivak/sftpserver
Author: Ruslan Spivak
Author-email: ruslan.spivak@gmail.com
License: MIT
Platform: UNKNOWN
Classifier: Intended Audience :: Developers
Classifier: License :: OSI Approved :: MIT License
Classifier: Programming Language :: Python
Classifier: Topic :: Internet :: File Transfer Protocol (FTP)
Classifier: Operating System :: Unix
Requires-Dist: paramiko
Requires-Dist: setuptools (>=0.7)
Provides-Extra: test
